aqicn_server.py
mseep_aqicn_mcp-0.1.3.dist-info/licenses/LICENSE
mseep_aqicn_mcp-0.1.3.dist-info/METADATA
mseep_aqicn_mcp-0.1.3.dist-info/WHEEL
mseep_aqicn_mcp-0.1.3.dist-info/top_level.txt
mseep_aqicn_mcp-0.1.3.dist-info/RECORD
