Metadata-Version: 2.4
Name: mseep-aqicn-mcp
Version: 0.1.3
Summary: MCP server for fetching air quality data from AQICN
Author-email: mseep <support@skydeck.ai>
Requires-Python: >=3.13
License-File: LICENSE
Requires-Dist: mcp[cli]
Requires-Dist: httpx
Requires-Dist: pydantic>=2.0.0
Requires-Dist: python-dotenv>=1.0.0
Dynamic: license-file
